dunedn/__init__.py
dunedn/configdn.py
dunedn/geometry/__init__.py
dunedn/geometry/helpers.py
dunedn/geometry/pdune.py
dunedn/preprocessing/__init__.py
dunedn/preprocessing/efficiency.py
dunedn/preprocessing/larsoft_products_processing.py
dunedn/preprocessing/preprocess.py
dunedn/preprocessing/preprocess_recob.py
dunedn/preprocessing/putils.py
dunedn/scripts/__init__.py
dunedn/scripts/dunedn.py
dunedn/tests/__init__.py
dunedn/tests/test_config.py
dunedn/tests/test_networks.py
dunedn/training/__init__.py
dunedn/training/args.py
dunedn/training/dataloader.py
dunedn/training/denoise_training.py
dunedn/training/losses.py
dunedn/training/ssim.py
dunedn/training/train.py
dunedn/utils/__init__.py
dunedn/utils/utils.py
dunedn-1.0.1.dist-info/LICENSE
dunedn-1.0.1.dist-info/METADATA
dunedn-1.0.1.dist-info/WHEEL
dunedn-1.0.1.dist-info/entry_points.txt
dunedn-1.0.1.dist-info/top_level.txt
dunedn-1.0.1.dist-info/RECORD
