Metadata-Version: 2.1
Name: dunedn
Version: 1.0.1
Summary: ProtoDUNE raw data denoising with DL
Home-page: https://github.com/marcorossi5/DUNEdn.git
Author: M. Rossi
Author-email: marco.rossi@cern.ch
License: UNKNOWN
Download-URL: https://github.com/marcorossi5/DUNEdn/archive/refs/tags/1.0.0.tar.gz
Platform: UNKNOWN
Classifier: Operating System :: Unix
Classifier: Programming Language :: Python
Classifier: Programming Language :: Python :: 3
Classifier: Topic :: Scientific/Engineering
Classifier: Topic :: Scientific/Engineering :: Physics
Requires-Python: >=3.6
License-File: LICENSE
Requires-Dist: numpy
Requires-Dist: pyyaml
Requires-Dist: torch
Requires-Dist: torchvision
Requires-Dist: matplotlib
Requires-Dist: hyperopt
